

{"JetStream3.0":{"metrics":{"Score":["Geometric"]},"tests":{"zlib-wasm":{"metrics":{"Score":{"current":[99.36310600069748]},"Time":["Geometric"]},"tests":{"First":{"metrics":{"Time":{"current":[53.976]}}},"Worst":{"metrics":{"Time":{"current":[49.32849999999996]}}},"Average":{"metrics":{"Time":{"current":[47.85594871794868]}}}}},"WSL":{"metrics":{"Score":{"current":[3.568447453375701]},"Time":["Geometric"]},"tests":{"Stdlib":{"metrics":{"Time":{"current":[522.185]}}},"MainRun":{"metrics":{"Time":{"current":[3759.733]}}}}},"web-ssr":{"metrics":{"Score":{"current":[162.19076297231067]},"Time":["Geometric"]},"tests":{"First":{"metrics":{"Time":{"current":[36.264000000000124]}}},"Worst":{"metrics":{"Time":{"current":[29.07524999999987]}}},"Average":{"metrics":{"Time":{"current":[27.786413793103467]}}}}},"validatorjs":{"metrics":{"Score":{"current":[351.2474943270736]},"Time":["Geometric"]},"tests":{"First":{"metrics":{"Time":{"current":[58.47199999999975]}}},"Worst":{"metrics":{"Time":{"current":[8.020250000000033]}}},"Average":{"metrics":{"Time":{"current":[6.150840336134414]}}}}},"UniPoker":{"metrics":{"Score":{"current":[640.8829197537631]},"Time":["Geometric"]},"tests":{"First":{"metrics":{"Time":{"current":[11.52599999999984]}}},"Worst":{"metrics":{"Time":{"current":[6.724250000000666]}}},"Average":{"metrics":{"Time":{"current":[6.127050420168164]}}}}},"typescript-lib":{"metrics":{"Score":{"current":[5.129967732502967]},"Time":["Geometric"]},"tests":{"First":{"metrics":{"Time":{"current":[974.664999999999]}}}}},"tsf-wasm":{"metrics":{"Score":{"current":[216.7607184124355]},"Time":["Geometric"]},"tests":{"First":{"metrics":{"Time":{"current":[38.64800000000105]}}},"Worst":{"metrics":{"Time":{"current":[18.578250000000025]}}},"Average":{"metrics":{"Time":{"current":[17.09371428571426]}}}}},"transformersjs-bert-wasm":{"metrics":{"Score":{"current":[68.40459791377317]},"Time":["Geometric"]},"tests":{"First":{"metrics":{"Time":{"current":[406.9260000000013]}}},"Worst":{"metrics":{"Time":{"current":[31.688249999999698]}}},"Average":{"metrics":{"Time":{"current":[30.285896551724047]}}}}},"threejs":{"metrics":{"Score":{"current":[46.68358680231986]},"Time":["Geometric"]},"tests":{"First":{"metrics":{"Time":{"current":[507.63400000000007]}}},"Worst":{"metrics":{"Time":{"current":[53.02525000000014]}}},"Average":{"metrics":{"Time":{"current":[45.64402521008397]}}}}},"sync-fs":{"metrics":{"Score":{"current":[416.1248841826506]},"Time":["Geometric"]},"tests":{"First":{"metrics":{"Time":{"current":[17.80500000000029]}}},"Worst":{"metrics":{"Time":{"current":[10.456166666666832]}}},"Average":{"metrics":{"Time":{"current":[9.318037974683499]}}}}},"Sunspider":{"metrics":{"Score":{"current":[768.0005209214961]},"Time":["Geometric"]},"tests":{"First":{"metrics":{"Time":{"current":[9.636049549466815]}}},"Worst":{"metrics":{"Time":{"current":[5.974403996804782]}}},"Average":{"metrics":{"Time":{"current":[4.7932696117550515]}}}}},"stanford-crypto-sha256":{"metrics":{"Score":{"current":[1030.2238621029617]},"Time":["Geometric"]},"tests":{"First":{"metrics":{"Time":{"current":[6.435999999997875]}}},"Worst":{"metrics":{"Time":{"current":[4.401249999999891]}}},"Average":{"metrics":{"Time":{"current":[4.0357394957982935]}}}}},"stanford-crypto-pbkdf2":{"metrics":{"Score":{"current":[952.3588161843754]},"Time":["Geometric"]},"tests":{"First":{"metrics":{"Time":{"current":[7.021000000000641]}}},"Worst":{"metrics":{"Time":{"current":[4.821750000000975]}}},"Average":{"metrics":{"Time":{"current":[4.27468907563036]}}}}},"stanford-crypto-aes":{"metrics":{"Score":{"current":[475.8281200077198]},"Time":["Geometric"]},"tests":{"First":{"metrics":{"Time":{"current":[17.152000000001863]}}},"Worst":{"metrics":{"Time":{"current":[8.367749999998523]}}},"Average":{"metrics":{"Time":{"current":[8.08418487394955]}}}}},"sqlite3-wasm":{"metrics":{"Score":{"current":[89.19726620379322]},"Time":["Geometric"]},"tests":{"First":{"metrics":{"Time":{"current":[92.29299999999785]}}},"Worst":{"metrics":{"Time":{"current":[44.72250000000167]}}},"Average":{"metrics":{"Time":{"current":[42.673724137931174]}}}}},"splay":{"metrics":{"Score":{"current":[228.22301669056404]},"Time":["Geometric"]},"tests":{"First":{"metrics":{"Time":{"current":[24.888999999999214]}}},"Worst":{"metrics":{"Time":{"current":[36.16600000000016]}}},"Average":{"metrics":{"Time":{"current":[11.68217647058842]}}}}},"source-map-wtb":{"metrics":{"Score":{"current":[315.2811016616246]},"Time":["Geometric"]},"tests":{"First":{"metrics":{"Time":{"current":[25.53900000000067]}}},"Worst":{"metrics":{"Time":{"current":[14.314500000000407]}}},"Average":{"metrics":{"Time":{"current":[10.910285714285626]}}}}},"richards-wasm":{"metrics":{"Score":{"current":[189.62627273873775]},"Time":["Geometric"]},"tests":{"First":{"metrics":{"Time":{"current":[29.04899999999907]}}},"Worst":{"metrics":{"Time":{"current":[27.396500000000742]}}},"Average":{"metrics":{"Time":{"current":[23.035000000000224]}}}}},"richards":{"metrics":{"Score":{"current":[1044.518894595592]},"Time":["Geometric"]},"tests":{"First":{"metrics":{"Time":{"current":[7.775000000001455]}}},"Worst":{"metrics":{"Time":{"current":[3.831999999996697]}}},"Average":{"metrics":{"Time":{"current":[3.681588235294396]}}}}},"regexp-octane":{"metrics":{"Score":{"current":[593.6855295750141]},"Time":["Geometric"]},"tests":{"First":{"metrics":{"Time":{"current":[8.671999999998661]}}},"Worst":{"metrics":{"Time":{"current":[9.112250000000131]}}},"Average":{"metrics":{"Time":{"current":[7.559546218487176]}}}}},"raytrace-public-class-fields":{"metrics":{"Score":{"current":[592.9331237258697]},"Time":["Geometric"]},"tests":{"First":{"metrics":{"Time":{"current":[16.65099999999802]}}},"Worst":{"metrics":{"Time":{"current":[6.647000000000844]}}},"Average":{"metrics":{"Time":{"current":[5.417848739495631]}}}}},"raytrace-private-class-fields":{"metrics":{"Score":{"current":[518.8531165286134]},"Time":["Geometric"]},"tests":{"First":{"metrics":{"Time":{"current":[20.80500000000029]}}},"Worst":{"metrics":{"Time":{"current":[7.306499999998778]}}},"Average":{"metrics":{"Time":{"current":[5.887075630252146]}}}}},"raytrace":{"metrics":{"Score":{"current":[658.3959872919188]},"Time":["Geometric"]},"tests":{"First":{"metrics":{"Time":{"current":[12.823000000003958]}}},"Worst":{"metrics":{"Time":{"current":[6.322999999998501]}}},"Average":{"metrics":{"Time":{"current":[5.401764705881905]}}}}},"proxy-vue":{"metrics":{"Score":{"current":[629.9729410354582]},"Time":["Geometric"]},"tests":{"First":{"metrics":{"Time":{"current":[10.310999999994237]}}},"Worst":{"metrics":{"Time":{"current":[10.615249999998923]}}},"Average":{"metrics":{"Time":{"current":[4.567865546217945]}}}}},"proxy-mobx":{"metrics":{"Score":{"current":[1294.7664435088]},"Time":["Geometric"]},"tests":{"First":{"metrics":{"Time":{"current":[9.048999999999069]}}},"Worst":{"metrics":{"Time":{"current":[4.01383333333312]}}},"Average":{"metrics":{"Time":{"current":[1.585534818941409]}}}}},"prismjs-startup-es6":{"metrics":{"Score":{"current":[324.270471222842]},"Time":["Geometric"]},"tests":{"First":{"metrics":{"Time":{"current":[28.536999999996624]}}},"Worst":{"metrics":{"Time":{"current":[12.481249999998909]}}},"Average":{"metrics":{"Time":{"current":[10.292512605042393]}}}}},"prettier-wtb":{"metrics":{"Score":{"current":[78.56150845635425]},"Time":["Geometric"]},"tests":{"First":{"metrics":{"Time":{"current":[122.92300000000249]}}},"Worst":{"metrics":{"Time":{"current":[51.98099999999977]}}},"Average":{"metrics":{"Time":{"current":[40.34621428571336]}}}}},"postcss-wtb":{"metrics":{"Score":{"current":[32.52358838027725]},"Time":["Geometric"]},"tests":{"First":{"metrics":{"Time":{"current":[207.67299999999523]}}},"Worst":{"metrics":{"Time":{"current":[141.2435000000005]}}},"Average":{"metrics":{"Time":{"current":[123.87000000000054]}}}}},"pdfjs":{"metrics":{"Score":{"current":[229.94394395650974]},"Time":["Geometric"]},"tests":{"First":{"metrics":{"Time":{"current":[43.81899999999587]}}},"Worst":{"metrics":{"Time":{"current":[17.849749999999403]}}},"Average":{"metrics":{"Time":{"current":[13.144663865546189]}}}}},"OfflineAssembler":{"metrics":{"Score":{"current":[183.39288710993057]},"Time":["Geometric"]},"tests":{"First":{"metrics":{"Time":{"current":[37.07700000000477]}}},"Worst":{"metrics":{"Time":{"current":[25.211499999997613]}}},"Average":{"metrics":{"Time":{"current":[21.67999999999937]}}}}},"octane-code-load":{"metrics":{"Score":{"current":[1028.983990630288]},"Time":["Geometric"]},"tests":{"First":{"metrics":{"Time":{"current":[5.415000000000873]}}},"Worst":{"metrics":{"Time":{"current":[5.34099999999853]}}},"Average":{"metrics":{"Time":{"current":[3.9670084033615325]}}}}},"navier-stokes":{"metrics":{"Score":{"current":[890.5768209024371]},"Time":["Geometric"]},"tests":{"First":{"metrics":{"Time":{"current":[10.22899999999936]}}},"Worst":{"metrics":{"Time":{"current":[5.217499999998836]}}},"Average":{"metrics":{"Time":{"current":[3.31589075630234]}}}}},"multi-inspector-code-load":{"metrics":{"Score":{"current":[334.6597044052332]},"Time":["Geometric"]},"tests":{"First":{"metrics":{"Time":{"current":[25.527999999998432]}}},"Worst":{"metrics":{"Time":{"current":[27.174749999998312]}}},"Average":{"metrics":{"Time":{"current":[4.807478991596426]}}}}},"mobx-startup":{"metrics":{"Score":{"current":[153.6595185219236]},"Time":["Geometric"]},"tests":{"First":{"metrics":{"Time":{"current":[29.424999999995634]}}},"Worst":{"metrics":{"Time":{"current":[41.30933333333572]}}},"Average":{"metrics":{"Time":{"current":[28.34437931034511]}}}}},"ML":{"metrics":{"Score":{"current":[143.87581613320322]},"Time":["Geometric"]},"tests":{"First":{"metrics":{"Time":{"current":[43.43000000000029]}}},"Worst":{"metrics":{"Time":{"current":[32.22624999999789]}}},"Average":{"metrics":{"Time":{"current":[29.987966101693573]}}}}},"mandreel":{"metrics":{"Score":{"current":[140.0539571872396]},"Time":["Geometric"]},"tests":{"First":{"metrics":{"Time":{"current":[65.18500000000495]}}},"Worst":{"metrics":{"Time":{"current":[27.52274999999827]}}},"Average":{"metrics":{"Time":{"current":[25.362050632911654]}}}}},"lazy-collections":{"metrics":{"Score":{"current":[272.44900044332593]},"Time":["Geometric"]},"tests":{"First":{"metrics":{"Time":{"current":[19.527000000001863]}}},"Worst":{"metrics":{"Time":{"current":[18.49024999999892]}}},"Average":{"metrics":{"Time":{"current":[17.11890756302516]}}}}},"Kotlin-compose-wasm":{"metrics":{"Score":{"current":[5.433544233215664]},"Time":["Geometric"]},"tests":{"First":{"metrics":{"Time":{"current":[1238.2410000000018]}}},"Worst":{"metrics":{"Time":{"current":[806.8819999999978]}}},"Average":{"metrics":{"Time":{"current":[779.911250000001]}}}}},"json-stringify-inspector":{"metrics":{"Score":{"current":[295.7568094600863]},"Time":["Geometric"]},"tests":{"First":{"metrics":{"Time":{"current":[24.574000000000524]}}},"Worst":{"metrics":{"Time":{"current":[15.417499999999563]}}},"Average":{"metrics":{"Time":{"current":[12.753105263157954]}}}}},"json-parse-inspector":{"metrics":{"Score":{"current":[254.73170525587577]},"Time":["Geometric"]},"tests":{"First":{"metrics":{"Time":{"current":[17.976000000002387]}}},"Worst":{"metrics":{"Time":{"current":[22.081500000000233]}}},"Average":{"metrics":{"Time":{"current":[19.051947368421104]}}}}},"jsdom-d3-startup":{"metrics":{"Score":{"current":[15.37880868272487]},"Time":["Geometric"]},"tests":{"First":{"metrics":{"Time":{"current":[331.137999999999]}}},"Worst":{"metrics":{"Time":{"current":[330.84300000000076]}}},"Average":{"metrics":{"Time":{"current":[313.69742857142927]}}}}},"js-tokens":{"metrics":{"Score":{"current":[243.6270912096816]},"Time":["Geometric"]},"tests":{"First":{"metrics":{"Time":{"current":[28.639999999999418]}}},"Worst":{"metrics":{"Time":{"current":[18.350749999997788]}}},"Average":{"metrics":{"Time":{"current":[16.44774789915966]}}}}},"j2cl-box2d-wasm":{"metrics":{"Score":{"current":[202.48021326489695]},"Time":["Geometric"]},"tests":{"First":{"metrics":{"Time":{"current":[44.32699999999022]}}},"Worst":{"metrics":{"Time":{"current":[19.220000000001164]}}},"Average":{"metrics":{"Time":{"current":[17.67423076923147]}}}}},"hash-map":{"metrics":{"Score":{"current":[584.3002408366818]},"Time":["Geometric"]},"tests":{"First":{"metrics":{"Time":{"current":[12.161999999996624]}}},"Worst":{"metrics":{"Time":{"current":[12.692999999995664]}}},"Average":{"metrics":{"Time":{"current":[4.059126050419863]}}}}},"gbemu":{"metrics":{"Score":{"current":[160.54563960529248]},"Time":["Geometric"]},"tests":{"First":{"metrics":{"Time":{"current":[67.82499999999709]}}},"Worst":{"metrics":{"Time":{"current":[25.73475000000326]}}},"Average":{"metrics":{"Time":{"current":[17.30631932773113]}}}}},"gaussian-blur":{"metrics":{"Score":{"current":[289.4382303216755]},"Time":["Geometric"]},"tests":{"First":{"metrics":{"Time":{"current":[15.588000000003374]}}},"Worst":{"metrics":{"Time":{"current":[27.037250000001222]}}},"Average":{"metrics":{"Time":{"current":[12.2317731092435]}}}}},"FlightPlanner":{"metrics":{"Score":{"current":[813.1019962604834]},"Time":["Geometric"]},"tests":{"First":{"metrics":{"Time":{"current":[9.028999999994994]}}},"Worst":{"metrics":{"Time":{"current":[8.161500000001979]}}},"Average":{"metrics":{"Time":{"current":[3.1554789915976813]}}}}},"first-inspector-code-load":{"metrics":{"Score":{"current":[211.69692247045813]},"Time":["Geometric"]},"tests":{"First":{"metrics":{"Time":{"current":[27.61699999999837]}}},"Worst":{"metrics":{"Time":{"current":[24.415000000000873]}}},"Average":{"metrics":{"Time":{"current":[19.540386554622312]}}}}},"esprima-next-wtb":{"metrics":{"Score":{"current":[104.57892434991989]},"Time":["Geometric"]},"tests":{"First":{"metrics":{"Time":{"current":[68.92500000000291]}}},"Worst":{"metrics":{"Time":{"current":[40.653500000007625]}}},"Average":{"metrics":{"Time":{"current":[39.003428571430305]}}}}},"espree-wtb":{"metrics":{"Score":{"current":[82.40963833910357]},"Time":["Geometric"]},"tests":{"First":{"metrics":{"Time":{"current":[82.9320000000007]}}},"Worst":{"metrics":{"Time":{"current":[53.34850000000006]}}},"Average":{"metrics":{"Time":{"current":[50.48142857142999]}}}}},"earley-boyer":{"metrics":{"Score":{"current":[1029.8409415707897]},"Time":["Geometric"]},"tests":{"First":{"metrics":{"Time":{"current":[8.206999999994878]}}},"Worst":{"metrics":{"Time":{"current":[4.789499999998952]}}},"Average":{"metrics":{"Time":{"current":[2.9115546218478103]}}}}},"doxbee-promise":{"metrics":{"Score":{"current":[425.8255420413574]},"Time":["Geometric"]},"tests":{"First":{"metrics":{"Time":{"current":[14.115999999994528]}}},"Worst":{"metrics":{"Time":{"current":[12.98124999999709]}}},"Average":{"metrics":{"Time":{"current":[8.834596638655302]}}}}},"doxbee-async":{"metrics":{"Score":{"current":[475.57672305292215]},"Time":["Geometric"]},"tests":{"First":{"metrics":{"Time":{"current":[34.697000000000116]}}},"Worst":{"metrics":{"Time":{"current":[7.428749999991851]}}},"Average":{"metrics":{"Time":{"current":[4.508588235294217]}}}}},"dotnet-interp-wasm":{"metrics":{"Score":{"current":[16.849058013842903]},"Time":["Geometric"]},"tests":{"First":{"metrics":{"Time":{"current":[512.9249999999884]}}},"Worst":{"metrics":{"Time":{"current":[227.31900000000317]}}},"Average":{"metrics":{"Time":{"current":[224.1266666666666]}}}}},"dotnet-aot-wasm":{"metrics":{"Score":{"current":[38.11491167509536]},"Time":["Geometric"]},"tests":{"First":{"metrics":{"Time":{"current":[234.48099999999977]}}},"Worst":{"metrics":{"Time":{"current":[100.95200000000479]}}},"Average":{"metrics":{"Time":{"current":[95.36800000000014]}}}}},"delta-blue":{"metrics":{"Score":{"current":[1979.9154590655653]},"Time":["Geometric"]},"tests":{"First":{"metrics":{"Time":{"current":[7.161000000007334]}}},"Worst":{"metrics":{"Time":{"current":[2.045250000002852]}}},"Average":{"metrics":{"Time":{"current":[1.0996386554622153]}}}}},"Dart-flute-todomvc-wasm":{"metrics":{"Score":{"current":[41.14170984998894]},"Time":["Geometric"]},"tests":{"First":{"metrics":{"Time":{"current":[179.3929999999964]}}},"Worst":{"metrics":{"Time":{"current":[109.18449999999574]}}},"Average":{"metrics":{"Time":{"current":[91.64241379310361]}}}}},"crypto":{"metrics":{"Score":{"current":[1316.1617946063247]},"Time":["Geometric"]},"tests":{"First":{"metrics":{"Time":{"current":[6.5319999999919665]}}},"Worst":{"metrics":{"Time":{"current":[3.3897499999984575]}}},"Average":{"metrics":{"Time":{"current":[2.4761008403366462]}}}}},"chai-wtb":{"metrics":{"Score":{"current":[181.68145890774954]},"Time":["Geometric"]},"tests":{"First":{"metrics":{"Time":{"current":[44.361000000004424]}}},"Worst":{"metrics":{"Time":{"current":[23.2554999999993]}}},"Average":{"metrics":{"Time":{"current":[20.20464285714427]}}}}},"cdjs":{"metrics":{"Score":{"current":[250.77888857257736]},"Time":["Geometric"]},"tests":{"First":{"metrics":{"Time":{"current":[27.8920000000071]}}},"Worst":{"metrics":{"Time":{"current":[18.014999999999418]}}},"Average":{"metrics":{"Time":{"current":[15.77332203389763]}}}}},"Box2D":{"metrics":{"Score":{"current":[514.3805240145779]},"Time":["Geometric"]},"tests":{"First":{"metrics":{"Time":{"current":[34.244000000006054]}}},"Worst":{"metrics":{"Time":{"current":[7.2097499999945285]}}},"Average":{"metrics":{"Time":{"current":[3.720075630251477]}}}}},"bigint-noble-ed25519":{"metrics":{"Score":{"current":[107.83780190694986]},"Time":["Geometric"]},"tests":{"First":{"metrics":{"Time":{"current":[59.166000000012]}}},"Worst":{"metrics":{"Time":{"current":[42.305749999999534]}}},"Average":{"metrics":{"Time":{"current":[39.822206896551634]}}}}},"Basic":{"metrics":{"Score":{"current":[1029.6317400203534]},"Time":["Geometric"]},"tests":{"First":{"metrics":{"Time":{"current":[9.021999999997206]}}},"Worst":{"metrics":{"Time":{"current":[4.376500000002125]}}},"Average":{"metrics":{"Time":{"current":[2.9002436974780204]}}}}},"babylonjs-startup-es6":{"metrics":{"Score":{"current":[22.44090520200577]},"Time":["Geometric"]},"tests":{"First":{"metrics":{"Time":{"current":[227.77399999999034]}}},"Worst":{"metrics":{"Time":{"current":[221.6442500000012]}}},"Average":{"metrics":{"Time":{"current":[219.0928888888884]}}}}},"babylonjs-scene-es6":{"metrics":{"Score":{"current":[40.21302253250473]},"Time":["Geometric"]},"tests":{"First":{"metrics":{"Time":{"current":[180.6140000000014]}}},"Worst":{"metrics":{"Time":{"current":[103.16425000000527]}}},"Average":{"metrics":{"Time":{"current":[103.16425000000527]}}}}},"babylon-wtb":{"metrics":{"Score":{"current":[89.69763593229897]},"Time":["Geometric"]},"tests":{"First":{"metrics":{"Time":{"current":[97.81800000001385]}}},"Worst":{"metrics":{"Time":{"current":[44.20350000000326]}}},"Average":{"metrics":{"Time":{"current":[40.05821428571445]}}}}},"Babylon":{"metrics":{"Score":{"current":[942.2768039200048]},"Time":["Geometric"]},"tests":{"First":{"metrics":{"Time":{"current":[16.797000000005937]}}},"Worst":{"metrics":{"Time":{"current":[4.092250000001513]}}},"Average":{"metrics":{"Time":{"current":[2.1736050420165594]}}}}},"babel-wtb":{"metrics":{"Score":{"current":[124.34146858089527]},"Time":["Geometric"]},"tests":{"First":{"metrics":{"Time":{"current":[87.95500000000175]}}},"Worst":{"metrics":{"Time":{"current":[31.182000000007978]}}},"Average":{"metrics":{"Time":{"current":[23.708142857143166]}}}}},"babel-minify-wtb":{"metrics":{"Score":{"current":[100.2940933780095]},"Time":["Geometric"]},"tests":{"First":{"metrics":{"Time":{"current":[109.32200000000012]}}},"Worst":{"metrics":{"Time":{"current":[38.03149999999732]}}},"Average":{"metrics":{"Time":{"current":[29.801142857142885]}}}}},"async-fs":{"metrics":{"Score":{"current":[292.50247971298785]},"Time":["Geometric"]},"tests":{"First":{"metrics":{"Time":{"current":[24.023000000001048]}}},"Worst":{"metrics":{"Time":{"current":[15.318499999993946]}}},"Average":{"metrics":{"Time":{"current":[13.573063291139574]}}}}},"argon2-wasm":{"metrics":{"Score":{"current":[161.14188729031505]},"Time":["Geometric"]},"tests":{"First":{"metrics":{"Time":{"current":[34.24199999999837]}}},"Worst":{"metrics":{"Time":{"current":[29.61433333333116]}}},"Average":{"metrics":{"Time":{"current":[29.459379310343326]}}}}},"Air":{"metrics":{"Score":{"current":[539.0247664283314]},"Time":["Geometric"]},"tests":{"First":{"metrics":{"Time":{"current":[24.243000000002212]}}},"Worst":{"metrics":{"Time":{"current":[9.663249999997788]}}},"Average":{"metrics":{"Time":{"current":[3.4070168067235254]}}}}},"ai-astar":{"metrics":{"Score":{"current":[784.8188458884752]},"Time":["Geometric"]},"tests":{"First":{"metrics":{"Time":{"current":[6.861000000004423]}}},"Worst":{"metrics":{"Time":{"current":[9.337500000001455]}}},"Average":{"metrics":{"Time":{"current":[4.0363025210087065]}}}}},"acorn-wtb":{"metrics":{"Score":{"current":[56.68332118210575]},"Time":["Geometric"]},"tests":{"First":{"metrics":{"Time":{"current":[124.70700000000943]}}},"Worst":{"metrics":{"Time":{"current":[76.47499999999853]}}},"Average":{"metrics":{"Time":{"current":[71.96707142856965]}}}}},"8bitbench-wasm":{"metrics":{"Score":{"current":[25.8525393543844]},"Time":["Geometric"]},"tests":{"First":{"metrics":{"Time":{"current":[205.98000000001048]}}},"Worst":{"metrics":{"Time":{"current":[187.94550000000163]}}},"Average":{"metrics":{"Time":{"current":[186.87164285714348]}}}}}}}}


